{
    "baseline": {
        "bleu": 3.7,
        "r1": 0.22,
        "r2": 0.08,
        "rl": 0.22,
        "chrF": 24.67,
        "chrf++": 23.95,
        "meteor": 0.28,
        "bert_f1": 0.72,
        "length": 35.75,
        "len_ratio": 3.38
    },
    "0.5": {
        "bleu": 9.9,
        "r1": 0.31,
        "r2": 0.11,
        "rl": 0.3,
        "chrF": 27.01,
        "chrf++": 27.14,
        "meteor": 0.34,
        "bert_f1": 0.78,
        "length": 19.18,
        "len_ratio": 1.73
    },
    "0.6": {
        "bleu": 8.54,
        "r1": 0.29,
        "r2": 0.11,
        "rl": 0.29,
        "chrF": 26.99,
        "chrf++": 26.98,
        "meteor": 0.33,
        "bert_f1": 0.77,
        "length": 21.97,
        "len_ratio": 2.03
    },
    "0.7": {
        "bleu": 7.12,
        "r1": 0.28,
        "r2": 0.1,
        "rl": 0.27,
        "chrF": 26.62,
        "chrf++": 26.45,
        "meteor": 0.32,
        "bert_f1": 0.76,
        "length": 24.76,
        "len_ratio": 2.31
    },
    "0.8": {
        "bleu": 6.51,
        "r1": 0.27,
        "r2": 0.09,
        "rl": 0.27,
        "chrF": 26.57,
        "chrf++": 26.3,
        "meteor": 0.31,
        "bert_f1": 0.75,
        "length": 26.82,
        "len_ratio": 2.51
    },
    "0.9": {
        "bleu": 6.04,
        "r1": 0.26,
        "r2": 0.09,
        "rl": 0.26,
        "chrF": 26.63,
        "chrf++": 26.26,
        "meteor": 0.31,
        "bert_f1": 0.74,
        "length": 28.74,
        "len_ratio": 2.71
    },
    "1.0": {
        "bleu": 5.76,
        "r1": 0.26,
        "r2": 0.09,
        "rl": 0.25,
        "chrF": 26.52,
        "chrf++": 26.05,
        "meteor": 0.31,
        "bert_f1": 0.74,
        "length": 29.67,
        "len_ratio": 2.82
    }
}